Workbook
Name BS_Check: Model!$F$108
Name currency: Inp!$F$26
Name L_Scenarios: Scenarios!$D$12:$D$14
Name LiveScenario: Scenarios!$D$11
Name million: Inp!$F$12
Name S_Circularity: Cover!$D$15
Name S_Scenarios: Scenarios!$E$12
Name thousand: Inp!$F$13

Sheet Cover
C7: =Hist!B1 -> FED Manufacturing
C8: ="Financial Model for "&Hist!I6+1&" to "&Hist!I6+5 -> Financial Model for 2025 to 2029
C11: Modeler: | D11: Animashaun Jafar
C12: Version: | D12: Ver 1.01
C13: Circularity in model | D13: ="Currently "&S_Circularity&" in the Net Interest Expense Line of the P&L" -> Currently OFF in the Net Interest Expense Line of the P&L
C14: Model Base Year | D14: =Hist!I6 -> 2024
C15: Circularity Toggle >>> | D15: OFF

Sheet Hist
B1: FED Manufacturing
B2: Income Statement
B4: ($ Millions)
G6: 2022 | H6: 2023 | I6: 2024
B8: Revenue Growth | H8: 0.10350333 | I8: 0.086390331
B9: COGS (% of revenue) | G9: 0.71735387 | H9: 0.72797685 | I9: 0.72829834
B10: SG&A (% of revenue) | G10: 0.16261232 | H10: 0.15453797 | I10: 0.1496135
C12: Revenue | G12: 3194.1 | H12: 3524.7 | I12: 3829.2
C14: Cost of Sales | G14: 2291.3 | H14: 2565.9 | I14: 2788.8
C15: SG&A | G15: 519.4 | H15: 544.7 | I15: 572.9
C16: Total Costs | G16: =SUM(G14:G15) -> 2810.7 | H16: =SUM(H14:H15) -> 3110.6 | I16: =SUM(I14:I15) -> 3361.7
C18: Cost Adjustments - Gain / (Loss) | G18: -7 | H18: -4.2 | I18: 2
C19: EBITDA | G19: =G12-G16-G18 -> 390.4 | H19: =H12-H16-H18 -> 418.3 | I19: =I12-I16-I18 -> 465.5
C21: Depreciation & Amortization | G21: 95.1 | H21: 113.2 | I21: 126.2
C22: EBIT | G22: =G19-G21 -> 295.3 | H22: =H19-H21 -> 305.1 | I22: =I19-I21 -> 339.3
C24: Cost Adjustments - Gain / (Loss) | G24: 59.9 | H24: 57 | I24: 51.6
C25: Net Interest Expense | G25: 62 | H25: 56.6 | I25: 59.1
C26: EBT | G26: =G22-G24-G25 -> 173.4 | H26: =H22-H24-H25 -> 191.5 | I26: =I22-I24-I25 -> 228.6
C28: Current Taxes | G28: 47.806 | H28: 49.61 | I28: 59.444
C29: Deferred Income Taxes | G29: 16.9 | H29: 31.7 | I29: 24
C30: Total Income Taxes | G30: =SUM(G28:G29) -> 64.706 | H30: =SUM(H28:H29) -> 81.31 | I30: =SUM(I28:I29) -> 83.444
C32: Net Income | G32: =G26-G30 -> 108.694 | H32: =H26-H30 -> 110.19 | I32: =I26-I30 -> 145.156
C34: Preferred Dividend | G34: 0.544 | H34: 0.544 | I34: 0.544
C35: Net Income to Common | G35: =G32-G34 -> 108.15 | H35: =H32-H34 -> 109.646 | I35: =I32-I34 -> 144.612
B37: FED Manufacruring
B38: Cash Flow Statement
B40: ($ Millions)
G41: 2022 | H41: 2023 | I41: 2024
B43: Operating Activities
C44: Net Income | G44: 108.694 | H44: 110.19 | I44: 145.156
C45: Depreciation | G45: 95.1 | H45: 113.2 | I45: 126.2
C46: Deferred Income Taxes | G46: 16.9 | H46: 31.7 | I46: 24
C47: Changes in Working Capital | G47: -119 | H47: -4.5 | I47: -83.8
C48: Other | G48: 161.9 | H48: 164.2 | I48: 242.1
C49: Operating Cash Flow | G49: =SUM(G44:G48) -> 263.594 | H49: =SUM(H44:H48) -> 414.79 | I49: =SUM(I44:I48) -> 453.656
B51: Investing Activities
C52: CAPEX | G52: -134.4 | H52: -158.7 | I52: -194.1
C53: Asset Disposal | G53: 2 | H53: 3.4 | I53: 10.5
C54: Other | G54: -14.9 | H54: -11.3 | I54: -15.4
C55: Investing Cash Flow | G55: =SUM(G52:G54) -> -147.3 | H55: =SUM(H52:H54) -> -166.6 | I55: =SUM(I52:I54) -> -199
B57: Financing Activities
C58: Revolver Issuance / (Repayment) | G58: 10.3 | H58: =H96-G96 -> 589.5 | I58: =I96-H96 -> -200
C59: Variable Rate Long Term Debt Issuance / (Repayment) | G59: 0 | H59: 0 | I59: 0
C60: Fixed Rate Long Term Debt Issuance / (Repayment) | G60: -259.3 | H60: 4.7 | I60: -10
C61: Preferred Share Issuance/ (Buy-Back) | G61: 0 | H61: 0 | I61: 0
C62: Common Share Issuance/ (Buy-Back) | G62: 300.2 | H62: 0.5 | I62: -94
C63: Preferred Share Dividends | G63: -0.544 | H63: -0.544 | I63: -0.544
C64: Common Share Dividends | G64: -483 | H64: 0 | I64: 0
C65: Other | G65: -102.7 | H65: -46.3 | I65: -54.1
C66: Financing Cash Flow | G66: =SUM(G58:G65) -> -535.044 | H66: =SUM(H58:H65) -> 547.856 | I66: =SUM(I58:I65) -> -358.644
C68: Change in Cash Position | G68: =G49+G55+G66 -> -418.75 | H68: =H49+H55+H66 -> 796.046 | I68: =I49+I55+I66 -> -103.988
C69: Beginning Cash | G69: 542.4 | H69: =G70 -> 123.65 | I69: =H70 -> 919.696
C70: Ending Cash | G70: =G69+G68 -> 123.65 | H70: =H69+H68 -> 919.696 | I70: =I69+I68 -> 815.708
B72: FED Manufacruring
B73: Balance Sheet
B76: ($ Millions)
G77: 2022 | H77: 2023 | I77: 2024
B78: ASSETS
C79: Cash and Equivalents | G79: =G70 -> 123.65 | H79: =H70 -> 919.696 | I79: =I70 -> 815.708
C80: Accounts Receivable | G80: 266.6 | H80: 306.8 | I80: 308.4
C81: Inventory | G81: 532.7 | H81: 630.2 | I81: 685.9
C82: Other | G82: 51.4 | H82: 61 | I82: 65.3
C83: Total Current Assets | G83: =SUM(G79:G82) -> 974.35 | H83: =SUM(H79:H82) -> 1917.696 | I83: =SUM(I79:I82) -> 1875.308
C85: Net PP&E | G85: 515.3 | H85: 586.9 | I85: 636.6
C86: Goodwill | G86: 116 | H86: 115.9 | I86: 116
C87: Intangibles | G87: 219.9 | H87: 220.6 | I87: 207.9
C88: Deferred income taxes | G88: 14 | H88: 17.7 | I88: 28.8
C89: Other | G89: 145.9 | H89: 159.1 | I89: 132.5
C90: Total Long Term Assets | G90: =SUM(G85:G89) -> 1011.1 | H90: =SUM(H85:H89) -> 1100.2 | I90: =SUM(I85:I89) -> 1121.8
C92: Total Assets | G92: =G83+G90 -> 1985.45 | H92: =H83+H90 -> 3017.896 | I92: =I83+I90 -> 2997.108
B95: LIABILITIES AND EQUITY
C96: Bank Debt - Revolver | G96: 10.5 | H96: 600 | I96: 400
C97: Accounts Payable | G97: 547 | H97: 678.4 | I97: 650.3
C98: Other | G98: 206.6 | H98: 248.5 | I98: 266.2
C99: Total Current Liabilities | G99: =SUM(G96:G98) -> 764.1 | H99: =SUM(H96:H98) -> 1526.9 | I99: =SUM(I96:I98) -> 1316.5
C101: Variable Rate Long Term Debt | G101: 0 | H101: 0 | I101: 250
C102: Fixed Rate Long Term Debt | G102: 889.9 | H102: 1035.5 | I102: 896.6
C103: Other | G103: 324 | H103: 394.7 | I103: 367.4
C104: Total Long Term Liabilities | G104: =SUM(G101:G103) -> 1213.9 | H104: =SUM(H101:H103) -> 1430.2 | I104: =SUM(I101:I103) -> 1514
C106: Total Liabilities | G106: =G99+G104 -> 1978 | H106: =H99+H104 -> 2957.1 | I106: =I99+I104 -> 2830.5
C108: Preferred Shares | G108: 6.4 | H108: 6.4 | I108: 6.4
C109: Common Shares | G109: 365.3 | H109: 371.9 | I109: 346.4
C110: Retained Earnings | G110: -380.45 | H110: -331.104 | I110: -212.892
C111: Other | G111: 16.2 | H111: 13.6 | I111: 26.7
C112: Shareholder's Equity | G112: =SUM(G108:G111) -> 7.45 | H112: =SUM(H108:H111) -> 60.796 | I112: =SUM(I108:I111) -> 166.608
B114: Total Liabilities and Equity | G114: =G106+G112 -> 1985.45 | H114: =H106+H112 -> 3017.896 | I114: =I106+I112 -> 2997.108
G116: =G92-G114 -> 0 | H116: =H92-H114 -> 0 | I116: =I92-I114 -> 0

Sheet Summary
B2: =Hist!B1 -> FED Manufacturing
B3: Summary
J4: ="BS Check "&BS_Check -> BS Check OK | L4: =LiveScenario -> Scenario: Base Case
I6: Actual | J6: Actual | K6: Actual | L6: Forecast | M6: Forecast | N6: Forecast | O6: Forecast | P6: Forecast
D7: Description | E7: Units | F7: Trend | I7: =Hist!G6 -> 2022 | J7: =Hist!H6 -> 2023 | K7: =Hist!I6 -> 2024 | L7: =K7+1 -> 2025 | M7: =L7+1 -> 2026 | N7: =M7+1 -> 2027 | O7: =N7+1 -> 2028 | P7: =O7+1 -> 2029
B9: Model Summary
C10: Summary Based on Scenario: Base Case
C12: Revenue
D13: Gross Revenue | E13: $'m | I13: 3194.1 | J13: 3524.7 | K13: 3829.2 | L13: 3981.41 | M13: 4094.4926 | N13: 4274.2186 | O13: 4395.8286 | P13: 4588.1924
D14: Growth Rate | E14: %age | J14: 0.10350333 | K14: 0.086390331 | L14: 0.039749817 | M14: 0.028402651 | N14: 0.043894584 | O14: 0.028451967 | P14: 0.04376053
C16: EBITDA
D17: EBITDA | E17: $'m | I17: 390.4 | J17: 418.3 | K17: 465.5 | L17: 467.14462 | M17: 492.37058 | N17: 552.15834 | O17: 580.71676 | P17: 646.30457
D18: Growth Rate | E18: %age | J18: 0.071465164 | K18: 0.11283768 | L18: 0.0035330162 | M18: 0.054000334 | N18: 0.12142837 | O18: 0.051721432 | P18: 0.11294286
D19: EBITDA Margin | E19: %age | I19: 0.12222535 | J19: 0.11867677 | K19: 0.12156586 | L19: 0.11733145 | M19: 0.12025192 | N19: 0.12918346 | O19: 0.13210633 | P19: 0.14086257
C21: Net Profit
D22: Net Profit | E22: $'m | I22: 108.694 | J22: 110.19 | K22: 145.156 | L22: 174.79582 | M22: 201.06675 | N22: 239.07092 | O22: 256.75853 | P22: 302.1845
D23: Growth Rate | E23: %age | J23: 0.013763409 | K23: 0.31732462 | L23: 0.2041929 | M23: 0.15029491 | N23: 0.18901272 | O23: 0.07398478 | P23: 0.17692098
D24: Net Profit Margin | E24: %age | I24: 0.034029617 | J24: 0.031262235 | K24: 0.037907657 | L24: 0.043902995 | M24: 0.049106633 | N24: 0.055933245 | O24: 0.058409587 | P24: 0.065861341
C26: Dupont Analysis
D27: ROE | E27: %age | I27: 14.589799 | J27: 1.8124548 | K27: 0.87124268 | L27: 0.4995769 | M27: 0.36769774 | N27: 0.30668501 | O27: 0.25266751 | P27: 0.23688393
D28: Net Profit Margin | E28: %age | I28: 0.034029617 | J28: 0.031262235 | K28: 0.037907657 | L28: 0.043902995 | M28: 0.049106633 | N28: 0.055933245 | O28: 0.058409587 | P28: 0.065861341
D29: Asset Turnover | E29: multiple | I29: 1.6087537 | J29: 1.1679329 | K29: 1.2776316 | L29: 1.5326648 | M29: 1.5513802 | N29: 1.4918385 | O29: 1.4311922 | P29: 1.3903555
D30: Financial Leverage | E30: ratio | I30: 266.50336 | J30: 49.639713 | K30: 17.98898 | L30: 7.4243939 | M30: 4.8265027 | N30: 3.6753671 | O30: 3.022507 | P30: 2.5868973
C32: Summary Based on Scenario: Best Case
C34: Revenue
D35: Gross Revenue | E35: $'m | I35: 3194.1 | J35: 3524.7 | K35: 3829.2 | L35: 4052.605 | M35: 4242.3912 | N35: 4508.4235 | O35: 4720.2184 | P35: 5016.2186
D36: Growth Rate | E36: %age | J36: 0.10350333 | K36: 0.086390331 | L36: 0.058342474 | M36: 0.046830656 | N36: 0.062708123 | O36: 0.04697759 | P36: 0.062708996
C38: EBITDA
D39: EBITDA | E39: $'m | I39: 390.4 | J39: 418.3 | K39: 465.5 | L39: 566.43001 | M39: 703.92354 | N39: 887.85985 | O39: 1045.3463 | P39: 1256.3272
D40: Growth Rate | E40: %age | J40: 0.071465164 | K40: 0.11283768 | L40: 0.21682065 | M40: 0.24273701 | N40: 0.26130155 | O40: 0.17737756 | P40: 0.20182874
D41: EBITDA Margin | E41: %age | I41: 0.12222535 | J41: 0.11867677 | K41: 0.12156586 | L41: 0.13976936 | M41: 0.16592613 | N41: 0.19693355 | O41: 0.22146142 | P41: 0.25045304
C43: Net Profit
D44: Net Profit | E44: $'m | I44: 108.694 | J44: 110.19 | K44: 145.156 | L44: 239.33133 | M44: 339.16872 | N44: 460.19986 | O44: 568.92757 | P44: 716.26875
D45: Growth Rate | E45: %age | J45: 0.013763409 | K45: 0.31732462 | L45: 0.64878703 | M45: 0.41715135 | N45: 0.35684643 | O45: 0.23626194 | P45: 0.25898054
D46: Net Profit Margin | E46: %age | I46: 0.034029617 | J46: 0.031262235 | K46: 0.037907657 | L46: 0.05905617 | M46: 0.079947536 | N46: 0.10207556 | O46: 0.12052993 | P46: 0.14279058
C48: Dupont Analysis
D49: ROE | E49: %age | I49: 14.589799 | J49: 1.8124548 | K49: 0.87124268 | L49: 0.60779185 | M49: 0.49541189 | N49: 0.4310224 | O49: 0.37512679 | P49: 0.3480956
D50: Net Profit Margin | E50: %age | I50: 0.034029617 | J50: 0.031262235 | K50: 0.037907657 | L50: 0.05905617 | M50: 0.079947536 | N50: 0.10207556 | O50: 0.12052993 | P50: 0.14279058
D51: Asset Turnover | E51: multiple | I51: 1.6087537 | J51: 1.1679329 | K51: 1.2776316 | L51: 1.5395495 | M51: 1.5584004 | N51: 1.5470459 | O51: 1.4936927 | P51: 1.4262791
D52: Financial Leverage | E52: ratio | I52: 266.50336 | J52: 49.639713 | K52: 17.98898 | L52: 6.6849156 | M52: 3.9763288 | N52: 2.7294482 | O52: 2.0836364 | P52: 1.7092062
C55: Summary Based on Scenario: Worst Case
C57: Revenue
D58: Gross Revenue | E58: $'m | I58: 3194.1 | J58: 3524.7 | K58: 3829.2 | L58: 3942.695 | M58: 4015.2515 | N58: 4150.7463 | O58: 4227.3373 | P58: 4369.4326
D59: Growth Rate | E59: %age | J59: 0.10350333 | K59: 0.086390331 | L59: 0.02963935 | M59: 0.01840278 | N59: 0.033745027 | O59: 0.018452344 | P59: 0.033613421
C61: EBITDA
D62: EBITDA | E62: $'m | I62: 390.4 | J62: 418.3 | K62: 465.5 | L62: 400.33923 | M62: 348.91332 | N62: 325.31776 | O62: 268.01876 | P62: 238.5779
D63: Growth Rate | E63: %age | J63: 0.071465164 | K63: 0.11283768 | L63: -0.13998018 | M63: -0.12845582 | N63: -0.067625848 | O63: -0.1761324 | P63: -0.10984627
D64: EBITDA Margin | E64: %age | I64: 0.12222535 | J64: 0.11867677 | K64: 0.12156586 | L64: 0.10153949 | M64: 0.086897002 | N64: 0.078375728 | O64: 0.063401319 | P64: 0.054601575
C66: Net Profit
D67: Net Profit | E67: $'m | I67: 108.694 | J67: 110.19 | K67: 145.156 | L67: 131.37232 | M67: 106.77576 | N67: 87.555569 | O67: 45.428904 | P67: 23.062797
D68: Growth Rate | E68: %age | J68: 0.013763409 | K68: 0.31732462 | L68: -0.094957715 | M68: -0.18722786 | N68: -0.18000519 | O68: -0.48114204 | P68: -0.49233209
D69: Net Profit Margin | E69: %age | I69: 0.034029617 | J69: 0.031262235 | K69: 0.037907657 | L69: 0.033320436 | M69: 0.026592546 | N69: 0.021093934 | O69: 0.010746458 | P69: 0.0052782132
C71: Dupont Analysis
D72: ROE | E72: %age | I72: 14.589799 | J72: 1.8124548 | K72: 0.87124268 | L72: 0.41007749 | M72: 0.2356143 | N72: 0.15021814 | O72: 0.067223447 | P72: 0.03140009
D73: Net Profit Margin | E73: %age | I73: 0.034029617 | J73: 0.031262235 | K73: 0.037907657 | L73: 0.033320436 | M73: 0.026592546 | N73: 0.021093934 | O73: 0.010746458 | P73: 0.0052782132
D74: Asset Turnover | E74: multiple | I74: 1.6087537 | J74: 1.1679329 | K74: 1.2776316 | L74: 1.5296983 | M74: 1.5160542 | N74: 1.4414902 | O74: 1.367506 | P74: 1.3137635
D75: Financial Leverage | E75: ratio | I75: 266.50336 | J75: 49.639713 | K75: 17.98898 | L75: 8.0454337 | M75: 5.8442259 | N75: 4.9402977 | O75: 4.5743162 | P75: 4.5282124
C77: Summary Generator
C78: ="Summary Based on "&LiveScenario -> Summary Based on Scenario: Base Case
C80: Revenue
D81: Gross Revenue | E81: =currency -> $'m | I81: =Model!I11 -> 3194.1 | J81: =Model!J11 -> 3524.7 | K81: =Model!K11 -> 3829.2 | L81: =Model!L11 -> 3981.41 | M81: =Model!M11 -> 4094.4926 | N81: =Model!N11 -> 4274.2186 | O81: =Model!O11 -> 4395.8286 | P81: =Model!P11 -> 4588.1924
D82: Growth Rate | E82: %age | J82: =J81/I81-1 -> 0.10350333 | K82: =K81/J81-1 -> 0.086390331 | L82: =L81/K81-1 -> 0.039749817 | M82: =M81/L81-1 -> 0.028402651 | N82: =N81/M81-1 -> 0.043894584 | O82: =O81/N81-1 -> 0.028451967 | P82: =P81/O81-1 -> 0.04376053
C84: EBITDA
D85: EBITDA | E85: =currency -> $'m | I85: =Model!I16 -> 390.4 | J85: =Model!J16 -> 418.3 | K85: =Model!K16 -> 465.5 | L85: =Model!L16 -> 467.14462 | M85: =Model!M16 -> 492.37058 | N85: =Model!N16 -> 552.15834 | O85: =Model!O16 -> 580.71676 | P85: =Model!P16 -> 646.30457
D86: Growth Rate | E86: %age | J86: =J85/I85-1 -> 0.071465164 | K86: =K85/J85-1 -> 0.11283768 | L86: =L85/K85-1 -> 0.0035330162 | M86: =M85/L85-1 -> 0.054000334 | N86: =N85/M85-1 -> 0.12142837 | O86: =O85/N85-1 -> 0.051721432 | P86: =P85/O85-1 -> 0.11294286
D87: EBITDA Margin | E87: %age | I87: =Model!I29 -> 0.12222535 | J87: =Model!J29 -> 0.11867677 | K87: =Model!K29 -> 0.12156586 | L87: =Model!L29 -> 0.11733145 | M87: =Model!M29 -> 0.12025192 | N87: =Model!N29 -> 0.12918346 | O87: =Model!O29 -> 0.13210633 | P87: =Model!P29 -> 0.14086257
C89: Net Profit
D90: Net Profit | E90: =currency -> $'m | I90: =Model!I25 -> 108.694 | J90: =Model!J25 -> 110.19 | K90: =Model!K25 -> 145.156 | L90: =Model!L25 -> 177.09429 | M90: =Model!M25 -> 203.52493 | N90: =Model!N25 -> 235.69068 | O90: =Model!O25 -> 247.71792 | P90: =Model!P25 -> 284.44904
D91: Growth Rate | E91: %age | J91: =J90/I90-1 -> 0.013763409 | K91: =K90/J90-1 -> 0.31732462 | L91: =L90/K90-1 -> 0.22002732 | M91: =M90/L90-1 -> 0.14924619 | N91: =N90/M90-1 -> 0.1580433 | O91: =O90/N90-1 -> 0.051029753 | P91: =P90/O90-1 -> 0.148278
D92: Net Profit Margin | E92: %age | I92: =Model!I32 -> 0.034029617 | J92: =Model!J32 -> 0.031262235 | K92: =Model!K32 -> 0.037907657 | L92: =Model!L32 -> 0.044480293 | M92: =Model!M32 -> 0.049706997 | N92: =Model!N32 -> 0.055142402 | O92: =Model!O32 -> 0.056352953 | P92: =Model!P32 -> 0.061995884
C94: Dupont Analysis
D95: =Model!D31 -> ROE | E95: =Model!E31 -> %age | I95: =Model!I31 -> 14.589799 | J95: =Model!J31 -> 1.8124548 | K95: =Model!K31 -> 0.87124268 | L95: =Model!L31 -> 0.72857836 | M95: =Model!M31 -> 0.54785009 | N95: =Model!N31 -> 0.43899053 | O95: =Model!O31 -> 0.35010221 | P95: =Model!P31 -> 0.31595076
D96: =Model!D32 -> Net Profit Margin | E96: =Model!E32 -> %age | I96: =Model!I32 -> 0.034029617 | J96: =Model!J32 -> 0.031262235 | K96: =Model!K32 -> 0.037907657 | L96: =Model!L32 -> 0.044480293 | M96: =Model!M32 -> 0.049706997 | N96: =Model!N32 -> 0.055142402 | O96: =Model!O32 -> 0.056352953 | P96: =Model!P32 -> 0.061995884
D97: =Model!D33 -> Asset Turnover | E97: =Model!E33 -> multiple | I97: =Model!I33 -> 1.6087537 | J97: =Model!J33 -> 1.1679329 | K97: =Model!K33 -> 1.2776316 | L97: =Model!L33 -> 1.5983919 | M97: =Model!M33 -> 1.5450557 | N97: =Model!N33 -> 1.482563 | O97: =Model!O33 -> 1.4214336 | P97: =Model!P33 -> 1.3839487
D98: =Model!D34 -> Financial Leverage | E98: =Model!E34 -> ratio | I98: =Model!I34 -> 266.50336 | J98: =Model!J34 -> 49.639713 | K98: =Model!K34 -> 17.98898 | L98: =Model!L34 -> 10.247676 | M98: =Model!M34 -> 7.1334573 | N98: =Model!N34 -> 5.3697778 | O98: =Model!O34 -> 4.3707061 | P98: =Model!P34 -> 3.6824475

Sheet Inp
B2: =Hist!B1 -> FED Manufacturing
B3: Inputs & Assumptions
J4: ="BS Check "&BS_Check -> BS Check OK | L4: =LiveScenario -> Scenario: Base Case
I6: Actual | J6: Actual | K6: Actual | L6: Forecast | M6: Forecast | N6: Forecast | O6: Forecast | P6: Forecast
D7: Description | E7: Units | F7: Input | I7: =Hist!G6 -> 2022 | J7: =Hist!H6 -> 2023 | K7: =Hist!I6 -> 2024 | L7: =K7+1 -> 2025 | M7: =L7+1 -> 2026 | N7: =M7+1 -> 2027 | O7: =N7+1 -> 2028 | P7: =O7+1 -> 2029
B9: Inputs & Assumptions
C10: General Model Assumptions
D11: Days in a period | E11: days | I11: =DATE(I7,12,31)-DATE(I7,1,1)+1 -> 365 | J11: =DATE(J7,12,31)-DATE(J7,1,1)+1 -> 365 | K11: =DATE(K7,12,31)-DATE(K7,1,1)+1 -> 366 | L11: =DATE(L7,12,31)-DATE(L7,1,1)+1 -> 365 | M11: =DATE(M7,12,31)-DATE(M7,1,1)+1 -> 365 | N11: =DATE(N7,12,31)-DATE(N7,1,1)+1 -> 365 | O11: =DATE(O7,12,31)-DATE(O7,1,1)+1 -> 366 | P11: =DATE(P7,12,31)-DATE(P7,1,1)+1 -> 365
D12: Million constant | E12: divisor | F12: 1000000
D13: Thousand constant | E13: divisor | F13: 1000
C16: Model Style Guide
D17: Normal style | E17: number | F17: 1234.5
D18: Input cells | E18: number
D19: Percent | E19: %age | F19: 0.05
D20: Multiples | E20: times | F20: 5
D21: Linked cell | E21: number
D22: Units | E22: Text | F22: Text
D23: Headings 1 | E23: Text | F23: Text
D24: Headings 2 | E24: Text | F24: Text
D25: Headings 3 | E25: Text | F25: Text
D26: Currency | E26: currency | F26: $'m
D27: Subtotal | E27: number | F27: 1234.5
D28: Grand totals | E28: number | F28: 12345
C32: Revenue Assumptions
D33: Average Sales Price | E33: $ | K33: 11600
D34: Total Revenue | E34: =currency -> $'m | K34: =Hist!I12 -> 3829.2 | L34: ="<< "&_xlfn.FORMULATEXT(K34) -> << =Hist!I12
D35: Auxillary Sales | E35: =currency -> $'m | K35: 623.5
D36: Net Revenue | E36: =currency -> $'m | K36: =K34-K35 -> 3205.7 | L36: ="<< "&_xlfn.FORMULATEXT(K36) -> << =K34-K35
D37: Volume | E37: units | K37: =K36*million/K33 -> 276353.45 | L37: ="<< "&_xlfn.FORMULATEXT(K37) -> << =K36*million/K33
D38: Volume Constraint | E38: units | L38: 280000 | M38: 280000 | N38: 285000 | O38: 285000 | P38: 290000
D40: Price Growth | E40: %age | K40: =_xlfn.FORMULATEXT(L40)&">>" -> =Scenarios!L18>> | L40: =Scenarios!L18 -> 0.03 | M40: =Scenarios!M18 -> 0.03 | N40: =Scenarios!N18 -> 0.03 | O40: =Scenarios!O18 -> 0.03 | P40: =Scenarios!P18 -> 0.03
D41: Volume Growth | E41: %age | K41: =_xlfn.FORMULATEXT(L41)&">>" -> =Scenarios!L24>> | L41: =Scenarios!L24 -> 0.04 | M41: =Scenarios!M24 -> 0.04 | N41: =Scenarios!N24 -> 0.04 | O41: =Scenarios!O24 -> 0.04 | P41: =Scenarios!P24 -> 0.04
D42: Auxiliary Sales Growth | E42: %age | K42: =_xlfn.FORMULATEXT(L42)&">>" -> =Scenarios!L30>> | L42: =Scenarios!L30 -> 0.02 | M42: =Scenarios!M30 -> 0.02 | N42: =Scenarios!N30 -> 0.02 | O42: =Scenarios!O30 -> 0.02 | P42: =Scenarios!P30 -> 0.02
C45: Operating Cost Assumptions
D46: Fixed Costs | E46: %age | F46: =1-F47 -> 0.45
D47: Variable Costs | E47: %age | F47: 0.55
D48: Cost Inflation | E48: %age | K48: =_xlfn.FORMULATEXT(L48)&">>" -> =Scenarios!L36>> | L48: =Scenarios!L36 -> 0.025 | M48: =Scenarios!M36 -> 0.025 | N48: =Scenarios!N36 -> 0.025 | O48: =Scenarios!O36 -> 0.025 | P48: =Scenarios!P36 -> 0.025
D49: SG&A | L49: 635
C52: Capex & Depreciation Assumptions
C53: Capex (Tangible Assets
D54: Additions | E54: =currency -> $'m | L54: 245 | M54: 280 | N54: 265 | O54: 265 | P54: 265
D55: Depreciation technique | E55: text | F55: Reducing balance
C57: Useful Life (Tangible Assets
D58: Existing tangible assets useful life | E58: years | F58: 10
D59: New tangible assets useful life | E59: years | F59: 16
C61: Capex (Intangible Assets
D62: Software cost (Additions) | E62: =currency -> $'m | L62: 52 | M62: 52 | N62: 52 | O62: 52 | P62: 52
D63: Amortisation technique | E63: text | F63: Reducing balance
C65: Useful Life (Intangible Assets)
D66: Existing intangible assets useful life | E66: years | F66: 6
D67: New intangible assets useful life | E67: years | F67: 11
C70: Working Capital Assumptions
D72: =D11 -> Days in a period | E72: =E11 -> days | I72: =I11 -> 365 | J72: =J11 -> 365 | K72: =K11 -> 366 | L72: ="<< "&_xlfn.FORMULATEXT(K72) -> << =K11
C74: Extracts from Financials
D75: Revenue | E75: =currency -> $'m | I75: =Hist!G12 -> 3194.1 | J75: =Hist!H12 -> 3524.7 | K75: =Hist!I12 -> 3829.2 | L75: ="<< "&_xlfn.FORMULATEXT(K75) -> << =Hist!I12
D76: Cost of Sales | E76: =currency -> $'m | I76: =Hist!G14 -> 2291.3 | J76: =Hist!H14 -> 2565.9 | K76: =Hist!I14 -> 2788.8 | L76: ="<< "&_xlfn.FORMULATEXT(K76) -> << =Hist!I14
C78: Balances
D79: =Hist!C80 -> Accounts Receivable | E79: =currency -> $'m | I79: =Hist!G80 -> 266.6 | J79: =Hist!H80 -> 306.8 | K79: =Hist!I80 -> 308.4 | L79: ="<< "&_xlfn.FORMULATEXT(K79) -> << =Hist!I80
D80: =Hist!C81 -> Inventory | E80: =currency -> $'m | I80: =Hist!G81 -> 532.7 | J80: =Hist!H81 -> 630.2 | K80: =Hist!I81 -> 685.9 | L80: ="<< "&_xlfn.FORMULATEXT(K80) -> << =Hist!I81
D81: =Hist!C82 -> Other | E81: =currency -> $'m | I81: =Hist!G82 -> 51.4 | J81: =Hist!H82 -> 61 | K81: =Hist!I82 -> 65.3 | L81: ="<< "&_xlfn.FORMULATEXT(K81) -> << =Hist!I82
D82: =Hist!C97 -> Accounts Payable | E82: =currency -> $'m | I82: =Hist!G97 -> 547 | J82: =Hist!H97 -> 678.4 | K82: =Hist!I97 -> 650.3 | L82: ="<< "&_xlfn.FORMULATEXT(K82) -> << =Hist!I97
D83: =Hist!C98 -> Other | E83: =currency -> $'m | I83: =Hist!G98 -> 206.6 | J83: =Hist!H98 -> 248.5 | K83: =Hist!I98 -> 266.2 | L83: ="<< "&_xlfn.FORMULATEXT(K83) -> << =Hist!I98
C85: Days
D86: =D79 -> Accounts Receivable | E86: days | H86: =_xlfn.FORMULATEXT(I86)&">>" -> =I79/I$75*I$72>> | I86: =I79/I$75*I$72 -> 30.465233 | J86: =J79/J$75*J$72 -> 31.770647 | K86: =K79/K$75*K$72 -> 29.47728 | L86: 29.48 | M86: 29.48 | N86: 29.48 | O86: 29.48 | P86: 29.48
D87: =D80 -> Inventory | E87: days | H87: =_xlfn.FORMULATEXT(I87)&">>" -> =I80/I$76*I$72>> | I87: =I80/I$76*I$72 -> 84.858159 | J87: =J80/J$76*J$72 -> 89.646128 | K87: =K80/K$76*K$72 -> 90.016997 | L87: 90.02 | M87: 90.02 | N87: 90.02 | O87: 90.02 | P87: 90.02
D88: =D81 -> Other | E88: days | H88: =_xlfn.FORMULATEXT(I88)&">>" -> =I81/I$76*I$72>> | I88: =I81/I$76*I$72 -> 8.1879283 | J88: =J81/J$76*J$72 -> 8.6772672 | K88: =K81/K$76*K$72 -> 8.5699225 | L88: 8.57 | M88: 8.57 | N88: 8.57 | O88: 8.57 | P88: 8.57
D89: =D82 -> Accounts Payable | E89: days | H89: =_xlfn.FORMULATEXT(I89)&">>" -> =I82/I$76*I$72>> | I89: =I82/I$76*I$72 -> 87.136124 | J89: =J82/J$76*J$72 -> 96.502592 | K89: =K82/K$76*K$72 -> 85.34488 | L89: 85.34 | M89: 85.34 | N89: 85.34 | O89: 85.34 | P89: 85.34
D90: =D83 -> Other | E90: days | H90: =_xlfn.FORMULATEXT(I90)&">>" -> =I83/I$76*I$72>> | I90: =I83/I$76*I$72 -> 32.911011 | J90: =J83/J$76*J$72 -> 35.349195 | K90: =K83/K$76*K$72 -> 34.935886 | L90: 34.94 | M90: 34.94 | N90: 34.94 | O90: 34.94 | P90: 34.94
C92: Tax Assumptions
D93: Company Tax Rate | E93: %age | F93: 0.35
D94: Increase in PBT due to timing difference | E94: =currency -> $'m | L94: 24 | M94: 24 | N94: 24 | O94: 24 | P94: 24
C96: Debt Assumptions
C97: Interest Rates
D98: Interest on fixed rate debt | E98: %age | F98: 0.0655
D99: Interest on revolver | E99: %age | F99: 0.065
D100: Interest on excess cash | E100: %age | F100: 0.025
D101: Variable rate debt SOFR | E101: %age | F101: 0.052
D103: Spread on variable rate debt is determined using this grid below
D104: If Total Debt / EBITDA >= | F104: Spread to SOFR
D105: 0 | F105: 0.01
D106: 1 | F106: 0.015
D107: 2 | F107: 0.02
D108: 3 | F108: 0.025
D109: 4 | F109: 0.0275
D110: 4.5 | F110: 0.03
C113: Debt Repayment
D114: Fixed Rate term debt repayment | E114: =currency -> $'m | L114: 180 | M114: 180 | N114: 180 | O114: 180 | P114: 180
D115: Variable Rate term debt repayment | E115: =currency -> $'m | L115: 35 | M115: 35 | N115: 35 | O115: 35 | P115: 35
C117: Equity Assumptions
D118: Preferred Shares issuance | E118: =currency -> $'m | L118: 48 | M118: 45 | N118: 45 | O118: 45 | P118: 45
D119: Common Shares buyback | E119: =currency -> $'m | L119: -90 | M119: -50 | N119: -32 | O119: -32 | P119: -32
D120: Preferred Shares Dividend Ratio | E120: %age | F120: 0.095
D121: Common Shares Dividend Ratio | E121: %age | F121: 0.32
C124: Other Assumptions
D125: =Hist!C18 -> Cost Adjustments - Gain / (Loss) | E125: =currency -> $'m | K125: =Hist!I18 -> 2 | L125: 0 | M125: 0 | N125: 0 | O125: 0 | P125: 0
D126: =Hist!C24 -> Cost Adjustments - Gain / (Loss) | E126: =currency -> $'m | K126: =Hist!I24 -> 51.6 | L126: 0 | M126: 0 | N126: 0 | O126: 0 | P126: 0
D127: =Hist!C86 -> Goodwill | E127: =currency -> $'m | K127: =Hist!I86 -> 116 | L127: 116 | M127: 116 | N127: 116 | O127: 116 | P127: 116
D128: =Hist!C89 -> Other | E128: =currency -> $'m | K128: =Hist!I89 -> 132.5 | L128: 132.5 | M128: 132.5 | N128: 132.5 | O128: 132.5 | P128: 132.5
D129: =Hist!C103 -> Other | E129: =currency -> $'m | K129: =Hist!I103 -> 367.4 | L129: 367.4 | M129: 367.4 | N129: 367.4 | O129: 367.4 | P129: 367.4
D130: =Hist!C53 -> Asset Disposal | E130: =currency -> $'m | K130: =Hist!I53 -> 10.5 | L130: 0 | M130: 0 | N130: 0 | O130: 0 | P130: 0
...

Sheet Scenarios
B2: =Hist!B1 -> FED Manufacturing
B3: Scenarios
J4: ="BS Check "&BS_Check -> BS Check OK | L4: =LiveScenario -> Scenario: Base Case
I6: Actual | J6: Actual | K6: Actual | L6: Forecast | M6: Forecast | N6: Forecast | O6: Forecast | P6: Forecast
D7: Description | E7: Units | F7: Input | I7: =Hist!G6 -> 2022 | J7: =Hist!H6 -> 2023 | K7: =Hist!I6 -> 2024 | L7: =K7+1 -> 2025 | M7: =L7+1 -> 2026 | N7: =M7+1 -> 2027 | O7: =N7+1 -> 2028 | P7: =O7+1 -> 2029
B9: Scenario Analysis
C10: Scenarios
D11: {="Scenario: "&INDEX(L_Scenarios,S_Scenarios)} -> Scenario: Base Case
D12: Base Case | E12: 1
D13: Best Case
D14: Worst Case
C17: Price Growth Scenario
D18: Used in model | L18: {=INDEX(L19:L21,S_Scenarios)} -> 0.03 | M18: {=INDEX(M19:M21,S_Scenarios)} -> 0.03 | N18: {=INDEX(N19:N21,S_Scenarios)} -> 0.03 | O18: {=INDEX(O19:O21,S_Scenarios)} -> 0.03 | P18: {=INDEX(P19:P21,S_Scenarios)} -> 0.03
D19: Base Case | E19: %age | L19: 0.03 | M19: 0.03 | N19: 0.03 | O19: 0.03 | P19: 0.03
D20: Best Case | E20: %age | L20: 0.05 | M20: 0.05 | N20: 0.05 | O20: 0.05 | P20: 0.05
D21: Worst Case | E21: %age | L21: 0.02 | M21: 0.02 | N21: 0.02 | O21: 0.02 | P21: 0.02
C23: Volume Growth Scenario
D24: Used in model | L24: {=INDEX(L25:L27,S_Scenarios)} -> 0.04 | M24: {=INDEX(M25:M27,S_Scenarios)} -> 0.04 | N24: {=INDEX(N25:N27,S_Scenarios)} -> 0.04 | O24: {=INDEX(O25:O27,S_Scenarios)} -> 0.04 | P24: {=INDEX(P25:P27,S_Scenarios)} -> 0.04
D25: Base Case | E25: %age | L25: 0.04 | M25: 0.04 | N25: 0.04 | O25: 0.04 | P25: 0.04
D26: Best Case | E26: %age | L26: 0.06 | M26: 0.06 | N26: 0.06 | O26: 0.06 | P26: 0.06
D27: Worst Case | E27: %age | L27: 0.02 | M27: 0.02 | N27: 0.02 | O27: 0.02 | P27: 0.02
C29: Auxiliary Revenue Growth
D30: Used in model | L30: {=INDEX(L31:L33,S_Scenarios)} -> 0.02 | M30: {=INDEX(M31:M33,S_Scenarios)} -> 0.02 | N30: {=INDEX(N31:N33,S_Scenarios)} -> 0.02 | O30: {=INDEX(O31:O33,S_Scenarios)} -> 0.02 | P30: {=INDEX(P31:P33,S_Scenarios)} -> 0.02
D31: Base Case | E31: %age | L31: 0.02 | M31: 0.02 | N31: 0.02 | O31: 0.02 | P31: 0.02
D32: Best Case | E32: %age | L32: 0.03 | M32: 0.03 | N32: 0.03 | O32: 0.03 | P32: 0.03
D33: Worst Case | E33: %age | L33: 0.01 | M33: 0.01 | N33: 0.01 | O33: 0.01 | P33: 0.01
C35: Cost Inflation Scenario
D36: Used in model | L36: {=INDEX(L37:L39,S_Scenarios)} -> 0.025 | M36: {=INDEX(M37:M39,S_Scenarios)} -> 0.025 | N36: {=INDEX(N37:N39,S_Scenarios)} -> 0.025 | O36: {=INDEX(O37:O39,S_Scenarios)} -> 0.025 | P36: {=INDEX(P37:P39,S_Scenarios)} -> 0.025
D37: Base Case | E37: %age | L37: 0.025 | M37: 0.025 | N37: 0.025 | O37: 0.025 | P37: 0.025
D38: Best Case | E38: %age | L38: 0.015 | M38: 0.015 | N38: 0.015 | O38: 0.015 | P38: 0.015
D39: Worst Case | E39: %age | L39: 0.035 | M39: 0.035 | N39: 0.035 | O39: 0.035 | P39: 0.035

Sheet Model
B2: =Hist!B1 -> FED Manufacturing
B3: Model & Schedules
J4: ="BS Check "&BS_Check -> BS Check OK | L4: =LiveScenario -> Scenario: Base Case
I6: Actual | J6: Actual | K6: Actual | L6: Forecast | M6: Forecast | N6: Forecast | O6: Forecast | P6: Forecast
D7: Description | E7: Units | F7: Input | I7: =Hist!G6 -> 2022 | J7: =Hist!H6 -> 2023 | K7: =Hist!I6 -> 2024 | L7: =K7+1 -> 2025 | M7: =L7+1 -> 2026 | N7: =M7+1 -> 2027 | O7: =N7+1 -> 2028 | P7: =O7+1 -> 2029
B9: Financial Statements
C10: Income Statement
D11: =Hist!C12 -> Revenue | E11: =currency -> $'m | I11: =Hist!G12 -> 3194.1 | J11: =Hist!H12 -> 3524.7 | K11: =Hist!I12 -> 3829.2 | L11: =L130 -> 3981.41 | M11: =M130 -> 4094.4926 | N11: =N130 -> 4274.2186 | O11: =O130 -> 4395.8286 | P11: =P130 -> 4588.1924 | Q11: =_xlfn.FORMULATEXT(L11) -> =L130
D12: =Hist!C14 -> Cost of Sales | E12: =currency -> $'m | I12: =Hist!G14 -> 2291.3 | J12: =Hist!H14 -> 2565.9 | K12: =Hist!I14 -> 2788.8 | L12: =L143 -> 2879.2654 | M12: =M143 -> 2951.247 | N12: =N143 -> 3054.9134 | O12: =O143 -> 3131.2863 | P12: =P143 -> 3240.9666 | Q12: =_xlfn.FORMULATEXT(L12) -> =L143
D13: =Hist!C15 -> SG&A | E13: =currency -> $'m | I13: =Hist!G15 -> 519.4 | J13: =Hist!H15 -> 544.7 | K13: =Hist!I15 -> 572.9 | L13: =L151 -> 635 | M13: =M151 -> 650.875 | N13: =N151 -> 667.14687 | O13: =O151 -> 683.82555 | P13: =P151 -> 700.92119 | Q13: =_xlfn.FORMULATEXT(L13) -> =L151
D14: =Hist!C16 -> Total Costs | E14: =currency -> $'m | I14: =I12+I13 -> 2810.7 | J14: =J12+J13 -> 3110.6 | K14: =K12+K13 -> 3361.7 | L14: =L12+L13 -> 3514.2654 | M14: =M12+M13 -> 3602.122 | N14: =N12+N13 -> 3722.0603 | O14: =O12+O13 -> 3815.1118 | P14: =P12+P13 -> 3941.8878 | Q14: =_xlfn.FORMULATEXT(L14) -> =L12+L13
D15: =Hist!C18 -> Cost Adjustments - Gain / (Loss) | E15: =currency -> $'m | I15: =Hist!G18 -> -7 | J15: =Hist!H18 -> -4.2 | K15: =Hist!I18 -> 2 | L15: =Inp!L125 -> 0 | M15: =Inp!M125 -> 0 | N15: =Inp!N125 -> 0 | O15: =Inp!O125 -> 0 | P15: =Inp!P125 -> 0 | Q15: =_xlfn.FORMULATEXT(L15) -> =Inp!L125
D16: =Hist!C19 -> EBITDA | E16: =currency -> $'m | I16: =I11-I14-I15 -> 390.4 | J16: =J11-J14-J15 -> 418.3 | K16: =K11-K14-K15 -> 465.5 | L16: =L11-L14-L15 -> 467.14462 | M16: =M11-M14-M15 -> 492.37058 | N16: =N11-N14-N15 -> 552.15834 | O16: =O11-O14-O15 -> 580.71676 | P16: =P11-P14-P15 -> 646.30457 | Q16: =_xlfn.FORMULATEXT(L16) -> =L11-L14-L15
D17: =Hist!C21 -> Depreciation & Amortization | E17: =currency -> $'m | I17: =Hist!G21 -> 95.1 | J17: =Hist!H21 -> 113.2 | K17: =Hist!I21 -> 126.2 | L17: =L173+L196 -> 118.34977 | M17: =M173+M196 -> 127.04926 | N17: =N173+N196 -> 134.98573 | O17: =O173+O196 -> 143.03134 | P17: =P173+P196 -> 151.08431 | Q17: =_xlfn.FORMULATEXT(L17) -> =L173+L196
D18: =Hist!C22 -> EBIT | E18: =currency -> $'m | I18: =I16-I17 -> 295.3 | J18: =J16-J17 -> 305.1 | K18: =K16-K17 -> 339.3 | L18: =L16-L17 -> 348.79485 | M18: =M16-M17 -> 365.32132 | N18: =N16-N17 -> 417.17261 | O18: =O16-O17 -> 437.68542 | P18: =P16-P17 -> 495.22026 | Q18: =_xlfn.FORMULATEXT(L18) -> =L16-L17
D19: =Hist!C24 -> Cost Adjustments - Gain / (Loss) | E19: =currency -> $'m | I19: =Hist!G24 -> 59.9 | J19: =Hist!H24 -> 57 | K19: =Hist!I24 -> 51.6 | L19: =Inp!L126 -> 0 | M19: =Inp!M126 -> 0 | N19: =Inp!N126 -> 0 | O19: =Inp!O126 -> 0 | P19: =Inp!P126 -> 0 | Q19: =_xlfn.FORMULATEXT(L19) -> =Inp!L126
D20: =Hist!C25 -> Net Interest Expense | E20: =currency -> $'m | I20: =Hist!G25 -> 62 | J20: =Hist!H25 -> 56.6 | K20: =Hist!I25 -> 59.1 | L20: =L326 -> 76.3421 | M20: =M326 -> 52.206041 | N20: =N326 -> 54.571556 | O20: =O326 -> 56.580929 | P20: =P326 -> 57.606353 | Q20: =_xlfn.FORMULATEXT(L20) -> =L326
D21: =Hist!C26 -> EBT | E21: =currency -> $'m | I21: =I18-I19-I20 -> 173.4 | J21: =J18-J19-J20 -> 191.5 | K21: =K18-K19-K20 -> 228.6 | L21: =L18-L19-L20 -> 272.45275 | M21: =M18-M19-M20 -> 313.11528 | N21: =N18-N19-N20 -> 362.60105 | O21: =O18-O19-O20 -> 381.1045 | P21: =P18-P19-P20 -> 437.61391 | Q21: =_xlfn.FORMULATEXT(L21) -> =L18-L19-L20
D22: =Hist!C28 -> Current Taxes | E22: =currency -> $'m | I22: =Hist!G28 -> 47.806 | J22: =Hist!H28 -> 49.61 | K22: =Hist!I28 -> 59.444 | L22: =L207 -> 103.75846 | M22: =M207 -> 117.99035 | N22: =N207 -> 135.31037 | O22: =O207 -> 141.78657 | P22: =P207 -> 161.56487 | Q22: =_xlfn.FORMULATEXT(L22) -> =L207
D23: =Hist!C29 -> Deferred Income Taxes | E23: =currency -> $'m | I23: =Hist!G29 -> 16.9 | J23: =Hist!H29 -> 31.7 | K23: =Hist!I29 -> 24 | L23: =-L208 -> -8.4 | M23: =-M208 -> -8.4 | N23: =-N208 -> -8.4 | O23: =-O208 -> -8.4 | P23: =-P208 -> -8.4 | Q23: =_xlfn.FORMULATEXT(L23) -> =-L208
D24: =Hist!C30 -> Total Income Taxes | E24: =currency -> $'m | I24: =I22+I23 -> 64.706 | J24: =J22+J23 -> 81.31 | K24: =K22+K23 -> 83.444 | L24: =L22+L23 -> 95.358461 | M24: =M22+M23 -> 109.59035 | N24: =N22+N23 -> 126.91037 | O24: =O22+O23 -> 133.38657 | P24: =P22+P23 -> 153.16487 | Q24: =_xlfn.FORMULATEXT(L24) -> =L22+L23
D25: =Hist!C32 -> Net Income | E25: =currency -> $'m | I25: =I21-I24 -> 108.694 | J25: =J21-J24 -> 110.19 | K25: =K21-K24 -> 145.156 | L25: =L21-L24 -> 177.09429 | M25: =M21-M24 -> 203.52493 | N25: =N21-N24 -> 235.69068 | O25: =O21-O24 -> 247.71792 | P25: =P21-P24 -> 284.44904 | Q25: =_xlfn.FORMULATEXT(L25) -> =L21-L24
D26: =Hist!C34 -> Preferred Dividend | E26: =currency -> $'m | I26: =Hist!G34 -> 0.544 | J26: =Hist!H34 -> 0.544 | K26: =Hist!I34 -> 0.544 | L26: =L338 -> 2.888 | M26: =M338 -> 7.3055 | N26: =N338 -> 11.5805 | O26: =O338 -> 15.8555 | P26: =P338 -> 20.1305 | Q26: =_xlfn.FORMULATEXT(L26) -> =L338
D27: =Hist!C35 -> Net Income to Common | E27: =currency -> $'m | I27: =Hist!G35 -> 108.15 | J27: =Hist!H35 -> 109.646 | K27: =Hist!I35 -> 144.612 | L27: =L25-L26 -> 174.20629 | M27: =M25-M26 -> 196.21943 | N27: =N25-N26 -> 224.11018 | O27: =O25-O26 -> 231.86242 | P27: =P25-P26 -> 264.31854 | Q27: =_xlfn.FORMULATEXT(L27) -> =L25-L26
D29: EBITDA Margin | E29: %age | I29: =I16/I11 -> 0.12222535 | J29: =J16/J11 -> 0.11867677 | K29: =K16/K11 -> 0.12156586 | L29: =L16/L11 -> 0.11733145 | M29: =M16/M11 -> 0.12025192 | N29: =N16/N11 -> 0.12918346 | O29: =O16/O11 -> 0.13210633 | P29: =P16/P11 -> 0.14086257 | Q29: =_xlfn.FORMULATEXT(L29) -> =L16/L11
C30: Dupont Analysis
D31: ROE | E31: %age | I31: =I25/I104 -> 14.589799 | J31: =J25/J104 -> 1.8124548 | K31: =K25/K104 -> 0.87124268 | L31: =L25/L104 -> 0.72857836 | M31: =M25/M104 -> 0.54785009 | N31: =N25/N104 -> 0.43899053 | O31: =O25/O104 -> 0.35010221 | P31: =P25/P104 -> 0.31595076 | Q31: =_xlfn.FORMULATEXT(L31) -> =L25/L104
D32: Net Profit Margin | E32: %age | I32: =I25/I11 -> 0.034029617 | J32: =J25/J11 -> 0.031262235 | K32: =K25/K11 -> 0.037907657 | L32: =L25/L11 -> 0.044480293 | M32: =M25/M11 -> 0.049706997 | N32: =N25/N11 -> 0.055142402 | O32: =O25/O11 -> 0.056352953 | P32: =P25/P11 -> 0.061995884 | Q32: =_xlfn.FORMULATEXT(L32) -> =L25/L11
D33: Asset Turnover | E33: multiple | I33: =I11/I85 -> 1.6087537 | J33: =J11/J85 -> 1.1679329 | K33: =K11/K85 -> 1.2776316 | L33: =L11/L85 -> 1.5983919 | M33: =M11/M85 -> 1.5450557 | N33: =N11/N85 -> 1.482563 | O33: =O11/O85 -> 1.4214336 | P33: =P11/P85 -> 1.3839487 | Q33: =_xlfn.FORMULATEXT(L33) -> =L11/L85
D34: Financial Leverage | E34: ratio | I34: =I85/I104 -> 266.50336 | J34: =J85/J104 -> 49.639713 | K34: =K85/K104 -> 17.98898 | L34: =L85/L104 -> 10.247676 | M34: =M85/M104 -> 7.1334573 | N34: =N85/N104 -> 5.3697778 | O34: =O85/O104 -> 4.3707061 | P34: =P85/P104 -> 3.6824475 | Q34: =_xlfn.FORMULATEXT(L34) -> =L85/L104
C39: Cashflow Statement
C40: =Hist!B43 -> Operating Activities
D41: =Hist!C44 -> Net Income | E41: $'m | I41: =Hist!G44 -> 108.694 | J41: =Hist!H44 -> 110.19 | K41: =Hist!I44 -> 145.156 | L41: =L25 -> 177.09429 | M41: =M25 -> 203.52493 | N41: =N25 -> 235.69068 | O41: =O25 -> 247.71792 | P41: =P25 -> 284.44904 | Q41: =_xlfn.FORMULATEXT(L41) -> =L25
D42: =Hist!C45 -> Depreciation | E42: $'m | I42: =Hist!G45 -> 95.1 | J42: =Hist!H45 -> 113.2 | K42: =Hist!I45 -> 126.2 | L42: =L17 -> 118.34977 | M42: =M17 -> 127.04926 | N42: =N17 -> 134.98573 | O42: =O17 -> 143.03134 | P42: =P17 -> 151.08431 | Q42: =_xlfn.FORMULATEXT(L42) -> =L17
D43: =Hist!C46 -> Deferred Income Taxes | E43: $'m | I43: =Hist!G46 -> 16.9 | J43: =Hist!H46 -> 31.7 | K43: =Hist!I46 -> 24 | L43: =L23 -> -8.4 | M43: =M23 -> -8.4 | N43: =N23 -> -8.4 | O43: =O23 -> -8.4 | P43: =P23 -> -8.4 | Q43: =_xlfn.FORMULATEXT(L43) -> =L23
D44: =Hist!C47 -> Changes in Working Capital | E44: $'m | I44: =Hist!G47 -> -119 | J44: =Hist!H47 -> -4.5 | K44: =Hist!I47 -> -83.8 | L44: =L234 -> -7.3676731 | M44: =M234 -> -4.8558723 | N44: =N234 -> -8.3556147 | O44: =O234 -> -4.8220074 | P44: =P234 -> -9.4806003 | Q44: =_xlfn.FORMULATEXT(L44) -> =L234
D45: =Hist!C48 -> Other | E45: $'m | I45: =Hist!G48 -> 161.9 | J45: =Hist!H48 -> 164.2 | K45: =Hist!I48 -> 242.1 | L45: =Inp!L131 -> 0 | M45: =Inp!M131 -> 0 | N45: =Inp!N131 -> 0 | O45: =Inp!O131 -> 0 | P45: =Inp!P131 -> 0 | Q45: =_xlfn.FORMULATEXT(L45) -> =Inp!L131
D46: =Hist!C49 -> Operating Cash Flow | E46: $'m | I46: =SUM(I41:I45) -> 263.594 | J46: =SUM(J41:J45) -> 414.79 | K46: =SUM(K41:K45) -> 453.656 | L46: =SUM(L41:L45) -> 279.67638 | M46: =SUM(M41:M45) -> 317.31832 | N46: =SUM(N41:N45) -> 353.9208 | O46: =SUM(O41:O45) -> 377.52725 | P46: =SUM(P41:P45) -> 417.65275 | Q46: =_xlfn.FORMULATEXT(L46) -> =SUM(L41:L45)
C48: =Hist!B51 -> Investing Activities | E48: $'m
D49: =Hist!C52 -> CAPEX | E49: $'m | I49: =Hist!G52 -> -134.4 | J49: =Hist!H52 -> -158.7 | K49: =Hist!I52 -> -194.1 | L49: =-SUM(L172,L195) -> -297 | M49: =-SUM(M172,M195) -> -332 | N49: =-SUM(N172,N195) -> -317 | O49: =-SUM(O172,O195) -> -317 | P49: =-SUM(P172,P195) -> -317 | Q49: =_xlfn.FORMULATEXT(L49) -> =-SUM(L172,L195)
D50: =Hist!C53 -> Asset Disposal | E50: $'m | I50: =Hist!G53 -> 2 | J50: =Hist!H53 -> 3.4 | K50: =Hist!I53 -> 10.5 | L50: =Inp!L130 -> 0 | M50: =Inp!M130 -> 0 | N50: =Inp!N130 -> 0 | O50: =Inp!O130 -> 0 | P50: =Inp!P130 -> 0 | Q50: =_xlfn.FORMULATEXT(L50) -> =Inp!L130
D51: =Hist!C54 -> Other | E51: $'m | I51: =Hist!G54 -> -14.9 | J51: =Hist!H54 -> -11.3 | K51: =Hist!I54 -> -15.4 | L51: =K82-L82 -> 0 | M51: =L82-M82 -> 0 | N51: =M82-N82 -> 0 | O51: =N82-O82 -> 0 | P51: =O82-P82 -> 0 | Q51: =_xlfn.FORMULATEXT(L51) -> =K82-L82
D52: =Hist!C55 -> Investing Cash Flow | E52: $'m | I52: =SUM(I49:I51) -> -147.3 | J52: =SUM(J49:J51) -> -166.6 | K52: =SUM(K49:K51) -> -199 | L52: =SUM(L49:L51) -> -297 | M52: =SUM(M49:M51) -> -332 | N52: =SUM(N49:N51) -> -317 | O52: =SUM(O49:O51) -> -317 | P52: =SUM(P49:P51) -> -317 | Q52: =_xlfn.FORMULATEXT(L52) -> =SUM(L49:L51)
C54: =Hist!B57 -> Financing Activities | E54: $'m
D55: =Hist!C58 -> Revolver Issuance / (Repayment) | E55: $'m | I55: =Hist!G58 -> 10.3 | J55: =Hist!H58 -> 589.5 | K55: =Hist!I58 -> -200 | L55: =L316 -> -400 | M55: =M316 -> 222.02702 | N55: =N316 -> 248.37496 | O55: =O316 -> 231.52422 | P55: =P316 -> 202.65968 | Q55: =_xlfn.FORMULATEXT(L55) -> =L316
D56: =Hist!C59 -> Variable Rate Long Term Debt Issuance / (Repayment) | E56: $'m | I56: =Hist!G59 -> 0 | J56: =Hist!H59 -> 0 | K56: =Hist!I59 -> 0 | L56: =-L258 -> -35 | M56: =-M258 -> -35 | N56: =-N258 -> -35 | O56: =-O258 -> -35 | P56: =-P258 -> -35 | Q56: =_xlfn.FORMULATEXT(L56) -> =-L258
D57: =Hist!C60 -> Fixed Rate Long Term Debt Issuance / (Repayment) | E57: $'m | I57: =Hist!G60 -> -259.3 | J57: =Hist!H60 -> 4.7 | K57: =Hist!I60 -> -10 | L57: =-L246 -> -180 | M57: =-M246 -> -180 | N57: =-N246 -> -180 | O57: =-O246 -> -180 | P57: =-P246 -> -176.6 | Q57: =_xlfn.FORMULATEXT(L57) -> =-L246
D58: =Hist!C61 -> Preferred Share Issuance/ (Buy-Back) | E58: $'m | I58: =Hist!G61 -> 0 | J58: =Hist!H61 -> 0 | K58: =Hist!I61 -> 0 | L58: =L335 -> 48 | M58: =M335 -> 45 | N58: =N335 -> 45 | O58: =O335 -> 45 | P58: =P335 -> 45 | Q58: =_xlfn.FORMULATEXT(L58) -> =L335
D59: =Hist!C62 -> Common Share Issuance/ (Buy-Back) | E59: $'m | I59: =Hist!G62 -> 300.2 | J59: =Hist!H62 -> 0.5 | K59: =Hist!I62 -> -94 | L59: =L345 -> -90 | M59: =M345 -> -50 | N59: =N345 -> -32 | O59: =O345 -> -32 | P59: =P345 -> -32 | Q59: =_xlfn.FORMULATEXT(L59) -> =L345
D60: =Hist!C63 -> Preferred Share Dividends | E60: $'m | I60: =Hist!G63 -> -0.544 | J60: =Hist!H63 -> -0.544 | K60: =Hist!I63 -> -0.544 | L60: =-L338 -> -2.888 | M60: =-M338 -> -7.3055 | N60: =-N338 -> -11.5805 | O60: =-O338 -> -15.8555 | P60: =-P338 -> -20.1305 | Q60: =_xlfn.FORMULATEXT(L60) -> =-L338
D61: =Hist!C64 -> Common Share Dividends | E61: $'m | I61: =Hist!G64 -> -483 | J61: =Hist!H64 -> 0 | K61: =Hist!I64 -> 0 | L61: =-L351 -> -55.746011 | M61: =-M351 -> -62.790219 | N61: =-N351 -> -71.715259 | O61: =-O351 -> -74.195975 | P61: =-P351 -> -84.581933 | Q61: =_xlfn.FORMULATEXT(L61) -> =-L351
D62: =Hist!C65 -> Other | E62: $'m | I62: =Hist!G65 -> -102.7 | J62: =Hist!H65 -> -46.3 | K62: =Hist!I65 -> -54.1 | L62: =(L95-K95)+(L103-K103) -> 0 | M62: =(M95-L95)+(M103-L103) -> 0 | N62: =(N95-M95)+(N103-M103) -> 0 | O62: =(O95-N95)+(O103-N103) -> 0 | P62: =(P95-O95)+(P103-O103) -> 0 | Q62: =_xlfn.FORMULATEXT(L62) -> =(L95-K95)+(L103-K103)
D63: =Hist!C66 -> Financing Cash Flow | E63: $'m | I63: =SUM(I55:I62) -> -535.044 | J63: =SUM(J55:J62) -> 547.856 | K63: =SUM(K55:K62) -> -358.644 | L63: =SUM(L55:L62) -> -715.63401 | M63: =SUM(M55:M62) -> -68.068696 | N63: =SUM(N55:N62) -> -36.920803 | O63: =SUM(O55:O62) -> -60.527253 | P63: =SUM(P55:P62) -> -100.65275 | Q63: =_xlfn.FORMULATEXT(L63) -> =SUM(L55:L62)
D65: =Hist!C68 -> Change in Cash Position | E65: $'m | I65: =Hist!G68 -> -418.75 | J65: =Hist!H68 -> 796.046 | K65: =Hist!I68 -> -103.988 | L65: =SUM(L46,L52,L63) -> -732.95763 | M65: =SUM(M46,M52,M63) -> -82.750373 | N65: =SUM(N46,N52,N63) -> 0 | O65: =SUM(O46,O52,O63) -> 0 | P65: =SUM(P46,P52,P63) -> 0 | Q65: =_xlfn.FORMULATEXT(L65) -> =SUM(L46,L52,L63)
D66: =Hist!C69 -> Beginning Cash | E66: $'m | I66: =Hist!G69 -> 542.4 | J66: =Hist!H69 -> 123.65 | K66: =Hist!I69 -> 919.696 | L66: =K67 -> 815.708 | M66: =L67 -> 82.750373 | N66: =M67 -> 0 | O66: =N67 -> 0 | P66: =O67 -> 0 | Q66: =_xlfn.FORMULATEXT(L66) -> =K67
D67: =Hist!C70 -> Ending Cash | E67: $'m | I67: =SUM(I65:I66) -> 123.65 | J67: =SUM(J65:J66) -> 919.696 | K67: =SUM(K65:K66) -> 815.708 | L67: =SUM(L65:L66) -> 82.750373 | M67: =SUM(M65:M66) -> 0 | N67: =SUM(N65:N66) -> 0 | O67: =SUM(O65:O66) -> 0 | P67: =SUM(P65:P66) -> 0 | Q67: =_xlfn.FORMULATEXT(L67) -> =SUM(L65:L66)
C70: Balance Sheet
C71: =Hist!B78 -> ASSETS
D72: =Hist!C79 -> Cash and Equivalents | E72: $'m | I72: =Hist!G79 -> 123.65 | J72: =Hist!H79 -> 919.696 | K72: =Hist!I79 -> 815.708 | L72: =MAX(L67,0) -> 82.750373 | M72: =MAX(M67,0) -> 0 | N72: =MAX(N67,0) -> 0 | O72: =MAX(O67,0) -> 0 | P72: =MAX(P67,0) -> 0 | Q72: =_xlfn.FORMULATEXT(L72) -> =MAX(L67,0)
D73: =Hist!C80 -> Accounts Receivable | E73: $'m | I73: =Hist!G80 -> 266.6 | J73: =Hist!H80 -> 306.8 | K73: =Hist!I80 -> 308.4 | L73: =L226 -> 321.56703 | M73: =M226 -> 330.70039 | N73: =N226 -> 345.21634 | O73: =O226 -> 354.06838 | P73: =P226 -> 370.5751 | Q73: =_xlfn.FORMULATEXT(L73) -> =L226
D74: =Hist!C81 -> Inventory | E74: $'m | I74: =Hist!G81 -> 532.7 | J74: =Hist!H81 -> 630.2 | K74: =Hist!I81 -> 685.9 | L74: =L227 -> 710.11362 | M74: =M227 -> 727.86646 | N74: =N227 -> 753.43372 | O74: =O227 -> 770.15954 | P74: =P227 -> 799.32004 | Q74: =_xlfn.FORMULATEXT(L74) -> =L227
D75: =Hist!C82 -> Other | E75: $'m | I75: =Hist!G82 -> 51.4 | J75: =Hist!H82 -> 61 | K75: =Hist!I82 -> 65.3 | L75: =L228 -> 67.603573 | M75: =M228 -> 69.293663 | N75: =N228 -> 71.727693 | O75: =O228 -> 73.320009 | P75: =P228 -> 76.09612 | Q75: =_xlfn.FORMULATEXT(L75) -> =L228
D76: =Hist!C83 -> Total Current Assets | E76: $'m | I76: =SUM(I72:I75) -> 974.35 | J76: =SUM(J72:J75) -> 1917.696 | K76: =SUM(K72:K75) -> 1875.308 | L76: =SUM(L72:L75) -> 1182.0346 | M76: =SUM(M72:M75) -> 1127.8605 | N76: =SUM(N72:N75) -> 1170.3778 | O76: =SUM(O72:O75) -> 1197.5479 | P76: =SUM(P72:P75) -> 1245.9913 | Q76: =_xlfn.FORMULATEXT(L76) -> =SUM(L72:L75)
D78: =Hist!C85 -> Net PP&E | E78: $'m | I78: =Hist!G85 -> 515.3 | J78: =Hist!H85 -> 586.9 | K78: =Hist!I85 -> 636.6 | L78: =L174 -> 802.6275 | M78: =M174 -> 993.47803 | N78: =N174 -> 1160.4864 | O78: =O174 -> 1318.9905 | P78: =P174 -> 1469.3283 | Q78: =_xlfn.FORMULATEXT(L78) -> =L174
D79: =Hist!C86 -> Goodwill | E79: $'m | I79: =Hist!G86 -> 116 | J79: =Hist!H86 -> 115.9 | K79: =Hist!I86 -> 116 | L79: =Inp!L127 -> 116 | M79: =Inp!M127 -> 116 | N79: =Inp!N127 -> 116 | O79: =Inp!O127 -> 116 | P79: =Inp!P127 -> 116 | Q79: =_xlfn.FORMULATEXT(L79) -> =Inp!L127
D80: =Hist!C87 -> Intangibles | E80: $'m | I80: =Hist!G87 -> 219.9 | J80: =Hist!H87 -> 220.6 | K80: =Hist!I87 -> 207.9 | L80: =L197 -> 220.52273 | M80: =M197 -> 234.62293 | N80: =N197 -> 249.6288 | O80: =O197 -> 265.09342 | P80: =P197 -> 280.67126 | Q80: =_xlfn.FORMULATEXT(L80) -> =L197
D81: =Hist!C88 -> Deferred income taxes | E81: $'m | I81: =Hist!G88 -> 14 | J81: =Hist!H88 -> 17.7 | K81: =Hist!I88 -> 28.8 | L81: =K81+L208 -> 37.2 | M81: =L81+M208 -> 45.6 | N81: =M81+N208 -> 54 | O81: =N81+O208 -> 62.4 | P81: =O81+P208 -> 70.8 | Q81: =_xlfn.FORMULATEXT(L81) -> =K81+L208
D82: =Hist!C89 -> Other | E82: $'m | I82: =Hist!G89 -> 145.9 | J82: =Hist!H89 -> 159.1 | K82: =Hist!I89 -> 132.5 | L82: =Inp!L128 -> 132.5 | M82: =Inp!M128 -> 132.5 | N82: =Inp!N128 -> 132.5 | O82: =Inp!O128 -> 132.5 | P82: =Inp!P128 -> 132.5 | Q82: =_xlfn.FORMULATEXT(L82) -> =Inp!L128
D83: =Hist!C90 -> Total Long Term Assets | E83: $'m | I83: =SUM(I78:I82) -> 1011.1 | J83: =SUM(J78:J82) -> 1100.2 | K83: =SUM(K78:K82) -> 1121.8 | L83: =SUM(L78:L82) -> 1308.8502 | M83: =SUM(M78:M82) -> 1522.201 | N83: =SUM(N78:N82) -> 1712.6152 | O83: =SUM(O78:O82) -> 1894.9839 | P83: =SUM(P78:P82) -> 2069.2996 | Q83: =_xlfn.FORMULATEXT(L83) -> =SUM(L78:L82)
D85: =Hist!C92 -> Total Assets | E85: $'m | I85: =I83+I76 -> 1985.45 | J85: =J83+J76 -> 3017.896 | K85: =K83+K76 -> 2997.108 | L85: =L83+L76 -> 2490.8848 | M85: =M83+M76 -> 2650.0615 | N85: =N83+N76 -> 2882.993 | O85: =O83+O76 -> 3092.5318 | P85: =P83+P76 -> 3315.2908 | Q85: =_xlfn.FORMULATEXT(L85) -> =L83+L76
C87: =Hist!B95 -> LIABILITIES AND EQUITY
D88: =Hist!C96 -> Bank Debt - Revolver | E88: $'m | I88: =Hist!G96 -> 10.5 | J88: =Hist!H96 -> 600 | K88: =Hist!I96 -> 400 | L88: =L317 -> 0 | M88: =M317 -> 222.02702 | N88: =N317 -> 470.40198 | O88: =O317 -> 701.9262 | P88: =P317 -> 904.58588 | Q88: =_xlfn.FORMULATEXT(L88) -> =L317
D89: =Hist!C97 -> Accounts Payable | E89: $'m | I89: =Hist!G97 -> 547 | J89: =Hist!H97 -> 678.4 | K89: =Hist!I97 -> 650.3 | L89: =L230 -> 673.19591 | M89: =M230 -> 690.02581 | N89: =N230 -> 714.26387 | O89: =O230 -> 730.12014 | P89: =P230 -> 757.76463 | Q89: =_xlfn.FORMULATEXT(L89) -> =L230
D90: =Hist!C98 -> Other | E90: $'m | I90: =Hist!G98 -> 206.6 | J90: =Hist!H98 -> 248.5 | K90: =Hist!I98 -> 266.2 | L90: =L231 -> 275.62064 | M90: =M231 -> 282.51115 | N90: =N231 -> 292.43473 | O90: =O231 -> 298.92662 | P90: =P231 -> 310.24486 | Q90: =_xlfn.FORMULATEXT(L90) -> =L231
D91: =Hist!C99 -> Total Current Liabilities | E91: $'m | I91: =SUM(I88:I90) -> 764.1 | J91: =SUM(J88:J90) -> 1526.9 | K91: =SUM(K88:K90) -> 1316.5 | L91: =SUM(L88:L90) -> 948.81655 | M91: =SUM(M88:M90) -> 1194.564 | N91: =SUM(N88:N90) -> 1477.1006 | O91: =SUM(O88:O90) -> 1730.973 | P91: =SUM(P88:P90) -> 1972.5954 | Q91: =_xlfn.FORMULATEXT(L91) -> =SUM(L88:L90)
D93: =Hist!C101 -> Variable Rate Long Term Debt | E93: $'m | I93: =Hist!G101 -> 0 | J93: =Hist!H101 -> 0 | K93: =Hist!I101 -> 250 | L93: =L259 -> 215 | M93: =M259 -> 180 | N93: =N259 -> 145 | O93: =O259 -> 110 | P93: =P259 -> 75 | Q93: =_xlfn.FORMULATEXT(L93) -> =L259
D94: =Hist!C102 -> Fixed Rate Long Term Debt | E94: $'m | I94: =Hist!G102 -> 889.9 | J94: =Hist!H102 -> 1035.5 | K94: =Hist!I102 -> 896.6 | L94: =L247 -> 716.6 | M94: =M247 -> 536.6 | N94: =N247 -> 356.6 | O94: =O247 -> 176.6 | P94: =P247 -> 0 | Q94: =_xlfn.FORMULATEXT(L94) -> =L247
D95: =Hist!C103 -> Other | E95: $'m | I95: =Hist!G103 -> 324 | J95: =Hist!H103 -> 394.7 | K95: =Hist!I103 -> 367.4 | L95: =Inp!L129 -> 367.4 | M95: =Inp!M129 -> 367.4 | N95: =Inp!N129 -> 367.4 | O95: =Inp!O129 -> 367.4 | P95: =Inp!P129 -> 367.4 | Q95: =_xlfn.FORMULATEXT(L95) -> =Inp!L129
D96: =Hist!C104 -> Total Long Term Liabilities | E96: $'m | I96: =SUM(I93:I95) -> 1213.9 | J96: =SUM(J93:J95) -> 1430.2 | K96: =SUM(K93:K95) -> 1514 | L96: =SUM(L93:L95) -> 1299 | M96: =SUM(M93:M95) -> 1084 | N96: =SUM(N93:N95) -> 869 | O96: =SUM(O93:O95) -> 654 | P96: =SUM(P93:P95) -> 442.4 | Q96: =_xlfn.FORMULATEXT(L96) -> =SUM(L93:L95)
D98: =Hist!C106 -> Total Liabilities | E98: $'m | I98: =I96+I91 -> 1978 | J98: =J96+J91 -> 2957.1 | K98: =K96+K91 -> 2830.5 | L98: =L96+L91 -> 2247.8165 | M98: =M96+M91 -> 2278.564 | N98: =N96+N91 -> 2346.1006 | O98: =O96+O91 -> 2384.973 | P98: =P96+P91 -> 2414.9954 | Q98: =_xlfn.FORMULATEXT(L98) -> =L96+L91
D100: =Hist!C108 -> Preferred Shares | E100: $'m | I100: =Hist!G108 -> 6.4 | J100: =Hist!H108 -> 6.4 | K100: =Hist!I108 -> 6.4 | L100: =L336 -> 54.4 | M100: =M336 -> 99.4 | N100: =N336 -> 144.4 | O100: =O336 -> 189.4 | P100: =P336 -> 234.4 | Q100: =_xlfn.FORMULATEXT(L100) -> =L336
D101: =Hist!C109 -> Common Shares | E101: $'m | I101: =Hist!G109 -> 365.3 | J101: =Hist!H109 -> 371.9 | K101: =Hist!I109 -> 346.4 | L101: =L346 -> 256.4 | M101: =M346 -> 206.4 | N101: =N346 -> 174.4 | O101: =O346 -> 142.4 | P101: =P346 -> 110.4 | Q101: =_xlfn.FORMULATEXT(L101) -> =L346
D102: =Hist!C110 -> Retained Earnings | E102: $'m | I102: =Hist!G110 -> -380.45 | J102: =Hist!H110 -> -331.104 | K102: =Hist!I110 -> -212.892 | L102: =L352 -> -94.431726 | M102: =M352 -> 38.997488 | N102: =N352 -> 191.39241 | O102: =O352 -> 349.05886 | P102: =P352 -> 528.79547 | Q102: =_xlfn.FORMULATEXT(L102) -> =L352
D103: =Hist!C111 -> Other | E103: $'m | I103: =Hist!G111 -> 16.2 | J103: =Hist!H111 -> 13.6 | K103: =Hist!I111 -> 26.7 | L103: =K103 -> 26.7 | M103: =L103 -> 26.7 | N103: =M103 -> 26.7 | O103: =N103 -> 26.7 | P103: =O103 -> 26.7 | Q103: =_xlfn.FORMULATEXT(L103) -> =K103
D104: =Hist!C112 -> Shareholder's Equity | E104: $'m | I104: =SUM(I100:I103) -> 7.45 | J104: =SUM(J100:J103) -> 60.796 | K104: =SUM(K100:K103) -> 166.608 | L104: =SUM(L100:L103) -> 243.06827 | M104: =SUM(M100:M103) -> 371.49749 | N104: =SUM(N100:N103) -> 536.89241 | O104: =SUM(O100:O103) -> 707.55886 | P104: =SUM(P100:P103) -> 900.29547 | Q104: =_xlfn.FORMULATEXT(L104) -> =SUM(L100:L103)
D106: =Hist!B114 -> Total Liabilities and Equity | E106: $'m | I106: =I98+I104 -> 1985.45 | J106: =J98+J104 -> 3017.896 | K106: =K98+K104 -> 2997.108 | L106: =L98+L104 -> 2490.8848 | M106: =M98+M104 -> 2650.0615 | N106: =N98+N104 -> 2882.993 | O106: =O98+O104 -> 3092.5318 | P106: =P98+P104 -> 3315.2908 | Q106: =_xlfn.FORMULATEXT(L106) -> =L98+L104
D108: Balance Check | E108: =currency -> $'m | F108: =IF(SUM(I108:P108)=0,"OK","ERROR") -> OK | I108: =I85-I106 -> 0 | J108: =J85-J106 -> 0 | K108: =K85-K106 -> 0 | L108: =L85-L106 -> 0 | M108: =M85-M106 -> 0 | N108: =N85-N106 -> 0 | O108: =O85-O106 -> 0 | P108: =P85-P106 -> 0 | Q108: =_xlfn.FORMULATEXT(L108) -> =L85-L106
B111: Schedules & Calculations
C112: Revenue Schedule
D113: =Inp!D40 -> Price Growth | E113: %age | L113: =Inp!L40 -> 0.03 | M113: =Inp!M40 -> 0.03 | N113: =Inp!N40 -> 0.03 | O113: =Inp!O40 -> 0.03 | P113: =Inp!P40 -> 0.03 | Q113: =_xlfn.FORMULATEXT(L113) -> =Inp!L40
D114: =Inp!D41 -> Volume Growth | E114: %age | L114: =Inp!L41 -> 0.04 | M114: =Inp!M41 -> 0.04 | N114: =Inp!N41 -> 0.04 | O114: =Inp!O41 -> 0.04 | P114: =Inp!P41 -> 0.04 | Q114: =_xlfn.FORMULATEXT(L114) -> =Inp!L41
C116: Core Revenue
D117: =Inp!D33 -> Average Sales Price | E117: =Inp!E33 -> $ | K117: =Inp!K33 -> 11600 | L117: =K117*(1+L113) -> 11948 | M117: =L117*(1+M113) -> 12306.44 | N117: =M117*(1+N113) -> 12675.633 | O117: =N117*(1+O113) -> 13055.902 | P117: =O117*(1+P113) -> 13447.579 | Q117: =_xlfn.FORMULATEXT(L117) -> =K117*(1+L113)
D118: =Inp!D37 -> Volume | E118: =Inp!E37 -> units | K118: =Inp!K37 -> 276353.45 | L118: =K118*(1+L114) -> 287407.59 | M118: =L118*(1+M114) -> 298903.89 | N118: =M118*(1+N114) -> 310860.05 | O118: =N118*(1+O114) -> 323294.45 | P118: =O118*(1+P114) -> 336226.22 | Q118: =_xlfn.FORMULATEXT(L118) -> =K118*(1+L114)
D119: =Inp!D38 -> Volume Constraint | E119: =Inp!E38 -> units | L119: =Inp!L38 -> 280000 | M119: =Inp!M38 -> 280000 | N119: =Inp!N38 -> 285000 | O119: =Inp!O38 -> 285000 | P119: =Inp!P38 -> 290000 | Q119: =_xlfn.FORMULATEXT(L119) -> =Inp!L38
D120: Actual Volume | E120: units | K120: =MIN(K118,K119) -> 276353.45 | L120: =MIN(L118,L119) -> 280000 | M120: =MIN(M118,M119) -> 280000 | N120: =MIN(N118,N119) -> 285000 | O120: =MIN(O118,O119) -> 285000 | P120: =MIN(P118,P119) -> 290000 | Q120: =_xlfn.FORMULATEXT(L120) -> =MIN(L118,L119)
D121: Core Revenue | E121: =currency -> $'m | L121: =L117*L120/million -> 3345.44 | M121: =M117*M120/million -> 3445.8032 | N121: =N117*N120/million -> 3612.5555 | O121: =O117*O120/million -> 3720.9321 | P121: =P117*P120/million -> 3899.798 | Q121: =_xlfn.FORMULATEXT(L121) -> =L117*L120/million
C123: Auxuliary Revenue
D124: =Inp!D35 -> Auxillary Sales | E124: =Inp!E35 -> $'m | K124: =Inp!K35 -> 623.5 | L124: =K124*(1+L125) -> 635.97 | M124: =L124*(1+M125) -> 648.6894 | N124: =M124*(1+N125) -> 661.66319 | O124: =N124*(1+O125) -> 674.89645 | P124: =O124*(1+P125) -> 688.39438 | Q124: =_xlfn.FORMULATEXT(L124) -> =K124*(1+L125)
D125: =Inp!D42 -> Auxiliary Sales Growth | E125: %age | L125: =Inp!L42 -> 0.02 | M125: =Inp!M42 -> 0.02 | N125: =Inp!N42 -> 0.02 | O125: =Inp!O42 -> 0.02 | P125: =Inp!P42 -> 0.02 | Q125: =_xlfn.FORMULATEXT(L125) -> =Inp!L42
...

Sheet Template
B2: =Hist!B1 -> FED Manufacturing
B3: Template
J4: ="BS Check "&BS_Check -> BS Check OK | L4: =LiveScenario -> Scenario: Base Case
I6: Actual | J6: Actual | K6: Actual | L6: Forecast | M6: Forecast | N6: Forecast | O6: Forecast | P6: Forecast
D7: Description | E7: Units | F7: Input | I7: =Hist!G6 -> 2022 | J7: =Hist!H6 -> 2023 | K7: =Hist!I6 -> 2024 | L7: =K7+1 -> 2025 | M7: =L7+1 -> 2026 | N7: =M7+1 -> 2027 | O7: =N7+1 -> 2028 | P7: =O7+1 -> 2029
